mcp_server_sentry/__init__.py
mcp_server_sentry/__main__.py
mcp_server_sentry/server.py
mcp_server_sentry-2025.1.14.dist-info/METADATA
mcp_server_sentry-2025.1.14.dist-info/WHEEL
mcp_server_sentry-2025.1.14.dist-info/entry_points.txt
mcp_server_sentry-2025.1.14.dist-info/RECORD
